{"trial_id": "07", "hyperparameters": {"space": [{"class_name": "Choice", "config": {"name": "capas", "default": 1, "conditions": [], "values": [1, 2, 3], "ordered": true}}, {"class_name": "Choice", "config": {"name": "neuronas_capa", "default": 8, "conditions": [], "values": [8, 16, 32, 64], "ordered": true}}], "values": {"capas": 1, "neuronas_capa": 64}}, "metrics": {"metrics": {"acc": {"direction": "max", "observations": [{"value": [0.439371258020401], "step": 0}]}, "loss": {"direction": "min", "observations": [{"value": [0.6890259087085724], "step": 0}]}, "val_acc": {"direction": "max", "observations": [{"value": [0.8776595890522003], "step": 0}]}, "val_loss": {"direction": "min", "observations": [{"value": [0.5688618421554565], "step": 0}]}}}, "score": 0.8776595890522003, "best_step": 0, "status": "COMPLETED", "message": null}